goodlog/__init__.py
goodlog/configuration.py
goodlog/factory.py
goodlog/filters.py
goodlog/formats.py
goodlog/py.typed
goodlog/extra_info/__init__.py
goodlog/extra_info/context.py
goodlog/extra_info/store.py
goodlog-0.0.1rc6.dist-info/METADATA
goodlog-0.0.1rc6.dist-info/WHEEL
goodlog-0.0.1rc6.dist-info/top_level.txt
goodlog-0.0.1rc6.dist-info/RECORD
