Metadata-Version: 2.4
Name: goodlog
Version: 0.0.1rc6
Summary: Do natural python logging in a natural manner
Author: Ben Ronen
Project-URL: Homepage, https://github.com/benronen8/goodlog
Project-URL: Documentation, https://benronen8.github.io/goodlog
Project-URL: Source, https://github.com/benronen8/goodlog
Project-URL: Issues, https://github.com/benronen8/goodlog/issues
Keywords: log,logs,logger,logging,utilities,utils
Classifier: Development Status :: 3 - Alpha
Classifier: Intended Audience :: Developers
Classifier: License :: OSI Approved :: MIT License
Classifier: Programming Language :: Python :: 3
Classifier: Programming Language :: Python :: 3.10
Classifier: Programming Language :: Python :: 3.11
Classifier: Programming Language :: Python :: 3.12
Requires-Python: <4,>=3.10
